[
  {
    "tables": [{ "x": 400, "y": 220, "angle": 0 }],
    "cup": { "x": 400, "y": 190, "angle": 0 }
  },
  {
    "tables": [{ "x": 400, "y": 200, "angle": -0.3 }],
    "cup": { "x": 400, "y": 168, "angle": -17 }
  },
  {
    "tables": [{ "x": 480, "y": 180, "angle": 1.57 }],
    "cup": { "x": 450, "y": 180, "angle": -90 }
  },
  {
    "tables": [
      { "x": 400, "y": 400, "angle": -0.3 },
      { "x": 240, "y": 250, "angle": -1.1 }
    ],
    "cup": { "x": 300, "y": 292, "angle": -17 }
  },
  {
    "cup": {
      "x": 700,
      "y": 330,
      "method": "rotate"
    }
  }
]
